<?xml version="1.0" encoding="UTF-8" ?>
<desktop>
    <UIControl Name="godexp_win" ClassName="CGUIWindow" Movable="yes" CanMoveOutOfFather="yes" LogicPos_x="640" LogicPos_y="330" Size_x="400" Size_y="340" AlignControl="\desktop" AlignType="Center" PopupSound="window_popup">
        <UIControl Name="back" ClassName="CGUIPatch" MoveFather="yes" Size_x="400" Size_y="340" AlignControl="\desktop\godexp_win" AlignType="Center" Text="凝聚神格" Font="龙字体" FontHeight="18" TextRect_top="8" TextRect_right="400" TextRect_bottom="340" TextColor="0xFFFFFFFF" ShadeColor="0xFF000000" TextAlign="CenterTop" PicColor="0xFFFFFFFF" AlphaWrite="Write" TopPicFileName="data\ui\main\l_sz_02.bmp" TopPicRect_left="73" TopPicRect_right="146" TopPicRect_bottom="73" MidPicFileName="data\ui\main\l_sz_02.bmp" MidPicRect_left="73" MidPicRect_top="73" MidPicRect_right="146" MidPicRect_bottom="146" DownPicFileName="data\ui\main\l_sz_02.bmp" DownPicRect_left="73" DownPicRect_top="146" DownPicRect_right="146" DownPicRect_bottom="219" LeftPicFileName="data\ui\main\l_sz_02.bmp" LeftPicRect_top="73" LeftPicRect_right="73" LeftPicRect_bottom="146" RightPicFileName="data\ui\main\l_sz_02.bmp" RightPicRect_left="146" RightPicRect_top="73" RightPicRect_right="219" RightPicRect_bottom="146" LeftTopPicFileName="data\ui\main\l_sz_02.bmp" LeftTopPicRect_right="73" LeftTopPicRect_bottom="73" RightTopPicFileName="data\ui\main\l_sz_02.bmp" RightTopPicRect_left="146" RightTopPicRect_right="219" RightTopPicRect_bottom="73" LeftDownPicFileName="data\ui\main\l_sz_02.bmp" LeftDownPicRect_top="146" LeftDownPicRect_right="73" LeftDownPicRect_bottom="219" RightDownPicFileName="data\ui\main\l_sz_02.bmp" RightDownPicRect_left="146" RightDownPicRect_top="146" RightDownPicRect_right="219" RightDownPicRect_bottom="219">
            <UIControl Name="word" ClassName="CGUIStaticEx" LogicPos_x="100" LogicPos_y="162" Size_x="200" Size_y="20" Text="30点信仰 → 30点凝聚度" Font="龙字体" FontHeight="15" TextRect_right="200" TextRect_bottom="20" TextColor="0xFFFFFFFF" ShadeColor="0xFF000000" TextAlign="Center" PicColor="0xFFFFFF" RowHeight="2" />
            <UIControl Name="closebutton" ClassName="CGUIButton" LogicPos_x="364" LogicPos_y="10" Size_x="25" Size_y="15" Font="龙字体" TextRect_right="25" TextRect_bottom="15" TextColor="0xFFFFFFFF" ShadeColor="0xFF290404" TextAlign="Center" PicFileName="data\ui\common\l-common.bmp" PicRect_left="339" PicRect_top="176" PicRect_right="364" PicRect_bottom="191" PicColor="0xFFFFFFFF" PushPicFileName="data\ui\common\l-common.bmp" PushPicRect_left="393" PushPicRect_top="176" PushPicRect_right="418" PushPicRect_bottom="191" PushPicColor="0xFFFFFFFF" PushTextColor="0xFF000000" PushShadeColor="0xFF290404" MovePicFileName="data\ui\common\l-common.bmp" MovePicRect_left="366" MovePicRect_top="176" MovePicRect_right="391" MovePicRect_bottom="191" MovePicColor="0xFFFFFFFF" MoveTextColor="0xFF000000" MoveShadeColor="0xFF290404" DisablePicColor="0xFFFFFFFF" DisableTextColor="0xFFFFF2A4" DisableShadeColor="0xFF290404" TopColor="0xFF000000" BottomColor="0xFFAFAFAF" />
            <UIControl Name="word0" ClassName="CGUIStatic" LogicPos_x="70" LogicPos_y="235" Size_x="40" Size_y="16" Text="神格" Font="龙字体" FontHeight="14" TextRect_right="40" TextRect_bottom="16" TextColor="0xFFFFFFFF" ShadeColor="0xFF000000" TextAlign="Center" PicColor="0xFFFFFF" />
            <UIControl Name="levelpic" ClassName="CGUIStatic" LogicPos_x="132" LogicPos_y="235" Size_x="198" Size_y="35" Font="龙字体" TextRect_right="178" TextRect_bottom="40" TextColor="0xFFFFF2A4" ShadeColor="0xFF290404" PicColor="0xFFFFFF">
                <UIControl Name="10" ClassName="CGUIStatic" LogicPos_x="5" LogicPos_y="17" Size_x="17" Size_y="15" Font="龙字体" TextRect_right="17" TextRect_bottom="15" TextColor="0xFFFFFFFF" ShadeColor="0xFF000000" TextAlign="Center" PicFileName="data\ui\main\l_sz_02.bmp" PicRect_left="237" PicRect_top="196" PicRect_right="254" PicRect_bottom="211" PicColor="0xFFFFFFFF">
                    <UIControl Name="get" ClassName="CGUIStatic" Invisible="yes" Size_x="17" Size_y="15" Font="龙字体" TextRect_right="17" TextRect_bottom="15" TextColor="0xFFFFFFFF" ShadeColor="0xFF000000" PicFileName="data\ui\main\l_sz_02.bmp" PicRect_left="218" PicRect_top="196" PicRect_right="235" PicRect_bottom="211" PicColor="0xFFFFFFFF" />
                </UIControl>
                <UIControl Name="0" ClassName="CGUIStatic" LogicPos_x="5" Size_x="17" Size_y="15" Font="龙字体" TextRect_right="17" TextRect_bottom="15" TextColor="0xFFFFFFFF" ShadeColor="0xFF000000" TextAlign="Center" PicFileName="data\ui\main\l_sz_02.bmp" PicRect_left="237" PicRect_top="196" PicRect_right="254" PicRect_bottom="211" PicColor="0xFFFFFFFF">
                    <UIControl Name="get" ClassName="CGUIStatic" Invisible="yes" Size_x="17" Size_y="15" Font="龙字体" TextRect_right="17" TextRect_bottom="15" TextColor="0xFFFFFFFF" ShadeColor="0xFF000000" PicFileName="data\ui\main\l_sz_02.bmp" PicRect_left="218" PicRect_top="196" PicRect_right="235" PicRect_bottom="211" PicColor="0xFFFFFFFF" />
                </UIControl>
                <UIControl Name="1" ClassName="CGUIStatic" LogicPos_x="24" Size_x="17" Size_y="15" Font="龙字体" TextRect_right="17" TextRect_bottom="15" TextColor="0xFFFFFFFF" ShadeColor="0xFF000000" TextAlign="Center" PicFileName="data\ui\main\l_sz_02.bmp" PicRect_left="237" PicRect_top="196" PicRect_right="254" PicRect_bottom="211" PicColor="0xFFFFFFFF">
                    <UIControl Name="get" ClassName="CGUIStatic" Invisible="yes" Size_x="17" Size_y="15" Font="龙字体" TextRect_right="17" TextRect_bottom="15" TextColor="0xFFFFFFFF" ShadeColor="0xFF000000" PicFileName="data\ui\main\l_sz_02.bmp" PicRect_left="218" PicRect_top="196" PicRect_right="235" PicRect_bottom="211" PicColor="0xFFFFFFFF" />
                </UIControl>
                <UIControl Name="2" ClassName="CGUIStatic" LogicPos_x="43" Size_x="17" Size_y="15" Font="龙字体" TextRect_right="17" TextRect_bottom="15" TextColor="0xFFFFFFFF" ShadeColor="0xFF000000" TextAlign="Center" PicFileName="data\ui\main\l_sz_02.bmp" PicRect_left="237" PicRect_top="196" PicRect_right="254" PicRect_bottom="211" PicColor="0xFFFFFFFF">
                    <UIControl Name="get" ClassName="CGUIStatic" Invisible="yes" Size_x="17" Size_y="15" Font="龙字体" TextRect_right="17" TextRect_bottom="15" TextColor="0xFFFFFFFF" ShadeColor="0xFF000000" PicFileName="data\ui\main\l_sz_02.bmp" PicRect_left="218" PicRect_top="196" PicRect_right="235" PicRect_bottom="211" PicColor="0xFFFFFFFF" />
                </UIControl>
                <UIControl Name="3" ClassName="CGUIStatic" LogicPos_x="62" Size_x="17" Size_y="15" Font="龙字体" TextRect_right="17" TextRect_bottom="15" TextColor="0xFFFFFFFF" ShadeColor="0xFF000000" TextAlign="Center" PicFileName="data\ui\main\l_sz_02.bmp" PicRect_left="237" PicRect_top="196" PicRect_right="254" PicRect_bottom="211" PicColor="0xFFFFFFFF">
                    <UIControl Name="get" ClassName="CGUIStatic" Invisible="yes" Size_x="17" Size_y="15" Font="龙字体" TextRect_right="17" TextRect_bottom="15" TextColor="0xFFFFFFFF" ShadeColor="0xFF000000" PicFileName="data\ui\main\l_sz_02.bmp" PicRect_left="218" PicRect_top="196" PicRect_right="235" PicRect_bottom="211" PicColor="0xFFFFFFFF" />
                </UIControl>
                <UIControl Name="4" ClassName="CGUIStatic" LogicPos_x="81" Size_x="17" Size_y="15" Font="龙字体" TextRect_right="17" TextRect_bottom="15" TextColor="0xFFFFFFFF" ShadeColor="0xFF000000" TextAlign="Center" PicFileName="data\ui\main\l_sz_02.bmp" PicRect_left="237" PicRect_top="196" PicRect_right="254" PicRect_bottom="211" PicColor="0xFFFFFFFF">
                    <UIControl Name="get" ClassName="CGUIStatic" Invisible="yes" Size_x="17" Size_y="15" Font="龙字体" TextRect_right="17" TextRect_bottom="15" TextColor="0xFFFFFFFF" ShadeColor="0xFF000000" PicFileName="data\ui\main\l_sz_02.bmp" PicRect_left="218" PicRect_top="196" PicRect_right="235" PicRect_bottom="211" PicColor="0xFFFFFFFF" />
                </UIControl>
                <UIControl Name="5" ClassName="CGUIStatic" LogicPos_x="100" Size_x="17" Size_y="15" Font="龙字体" TextRect_right="17" TextRect_bottom="15" TextColor="0xFFFFFFFF" ShadeColor="0xFF000000" TextAlign="Center" PicFileName="data\ui\main\l_sz_02.bmp" PicRect_left="237" PicRect_top="196" PicRect_right="254" PicRect_bottom="211" PicColor="0xFFFFFFFF">
                    <UIControl Name="get" ClassName="CGUIStatic" Invisible="yes" Size_x="17" Size_y="15" Font="龙字体" TextRect_right="17" TextRect_bottom="15" TextColor="0xFFFFFFFF" ShadeColor="0xFF000000" PicFileName="data\ui\main\l_sz_02.bmp" PicRect_left="218" PicRect_top="196" PicRect_right="235" PicRect_bottom="211" PicColor="0xFFFFFFFF" />
                </UIControl>
                <UIControl Name="6" ClassName="CGUIStatic" LogicPos_x="119" Size_x="17" Size_y="15" Font="龙字体" TextRect_right="17" TextRect_bottom="15" TextColor="0xFFFFFFFF" ShadeColor="0xFF000000" TextAlign="Center" PicFileName="data\ui\main\l_sz_02.bmp" PicRect_left="237" PicRect_top="196" PicRect_right="254" PicRect_bottom="211" PicColor="0xFFFFFFFF">
                    <UIControl Name="get" ClassName="CGUIStatic" Invisible="yes" Size_x="17" Size_y="15" Font="龙字体" TextRect_right="17" TextRect_bottom="15" TextColor="0xFFFFFFFF" ShadeColor="0xFF000000" PicFileName="data\ui\main\l_sz_02.bmp" PicRect_left="218" PicRect_top="196" PicRect_right="235" PicRect_bottom="211" PicColor="0xFFFFFFFF" />
                </UIControl>
                <UIControl Name="7" ClassName="CGUIStatic" LogicPos_x="138" Size_x="17" Size_y="15" Font="龙字体" TextRect_right="17" TextRect_bottom="15" TextColor="0xFFFFFFFF" ShadeColor="0xFF000000" TextAlign="Center" PicFileName="data\ui\main\l_sz_02.bmp" PicRect_left="237" PicRect_top="196" PicRect_right="254" PicRect_bottom="211" PicColor="0xFFFFFFFF">
                    <UIControl Name="get" ClassName="CGUIStatic" Invisible="yes" Size_x="17" Size_y="15" Font="龙字体" TextRect_right="17" TextRect_bottom="15" TextColor="0xFFFFFFFF" ShadeColor="0xFF000000" PicFileName="data\ui\main\l_sz_02.bmp" PicRect_left="218" PicRect_top="196" PicRect_right="235" PicRect_bottom="211" PicColor="0xFFFFFFFF" />
                </UIControl>
                <UIControl Name="8" ClassName="CGUIStatic" LogicPos_x="157" Size_x="17" Size_y="15" Font="龙字体" TextRect_right="17" TextRect_bottom="15" TextColor="0xFFFFFFFF" ShadeColor="0xFF000000" TextAlign="Center" PicFileName="data\ui\main\l_sz_02.bmp" PicRect_left="237" PicRect_top="196" PicRect_right="254" PicRect_bottom="211" PicColor="0xFFFFFFFF">
                    <UIControl Name="get" ClassName="CGUIStatic" Invisible="yes" Size_x="17" Size_y="15" Font="龙字体" TextRect_right="17" TextRect_bottom="15" TextColor="0xFFFFFFFF" ShadeColor="0xFF000000" PicFileName="data\ui\main\l_sz_02.bmp" PicRect_left="218" PicRect_top="196" PicRect_right="235" PicRect_bottom="211" PicColor="0xFFFFFFFF" />
                </UIControl>
                <UIControl Name="9" ClassName="CGUIStatic" LogicPos_x="176" Size_x="17" Size_y="15" Font="龙字体" TextRect_right="17" TextRect_bottom="15" TextColor="0xFFFFFFFF" ShadeColor="0xFF000000" TextAlign="Center" PicFileName="data\ui\main\l_sz_02.bmp" PicRect_left="237" PicRect_top="196" PicRect_right="254" PicRect_bottom="211" PicColor="0xFFFFFFFF">
                    <UIControl Name="get" ClassName="CGUIStatic" Invisible="yes" Size_x="17" Size_y="15" Font="龙字体" TextRect_right="17" TextRect_bottom="15" TextColor="0xFFFFFFFF" ShadeColor="0xFF000000" PicFileName="data\ui\main\l_sz_02.bmp" PicRect_left="218" PicRect_top="196" PicRect_right="235" PicRect_bottom="211" PicColor="0xFFFFFFFF" />
                </UIControl>
                <UIControl Name="11" ClassName="CGUIStatic" LogicPos_x="24" LogicPos_y="17" Size_x="17" Size_y="15" Font="龙字体" TextRect_right="17" TextRect_bottom="15" TextColor="0xFFFFFFFF" ShadeColor="0xFF000000" TextAlign="Center" PicFileName="data\ui\main\l_sz_02.bmp" PicRect_left="237" PicRect_top="196" PicRect_right="254" PicRect_bottom="211" PicColor="0xFFFFFFFF">
                    <UIControl Name="get" ClassName="CGUIStatic" Invisible="yes" Size_x="17" Size_y="15" Font="龙字体" TextRect_right="17" TextRect_bottom="15" TextColor="0xFFFFFFFF" ShadeColor="0xFF000000" PicFileName="data\ui\main\l_sz_02.bmp" PicRect_left="218" PicRect_top="196" PicRect_right="235" PicRect_bottom="211" PicColor="0xFFFFFFFF" />
                </UIControl>
                <UIControl Name="12" ClassName="CGUIStatic" LogicPos_x="43" LogicPos_y="17" Size_x="17" Size_y="15" Font="龙字体" TextRect_right="17" TextRect_bottom="15" TextColor="0xFFFFFFFF" ShadeColor="0xFF000000" TextAlign="Center" PicFileName="data\ui\main\l_sz_02.bmp" PicRect_left="237" PicRect_top="196" PicRect_right="254" PicRect_bottom="211" PicColor="0xFFFFFFFF">
                    <UIControl Name="get" ClassName="CGUIStatic" Invisible="yes" Size_x="17" Size_y="15" Font="龙字体" TextRect_right="17" TextRect_bottom="15" TextColor="0xFFFFFFFF" ShadeColor="0xFF000000" PicFileName="data\ui\main\l_sz_02.bmp" PicRect_left="218" PicRect_top="196" PicRect_right="235" PicRect_bottom="211" PicColor="0xFFFFFFFF" />
                </UIControl>
                <UIControl Name="13" ClassName="CGUIStatic" LogicPos_x="62" LogicPos_y="17" Size_x="17" Size_y="15" Font="龙字体" TextRect_right="17" TextRect_bottom="15" TextColor="0xFFFFFFFF" ShadeColor="0xFF000000" TextAlign="Center" PicFileName="data\ui\main\l_sz_02.bmp" PicRect_left="237" PicRect_top="196" PicRect_right="254" PicRect_bottom="211" PicColor="0xFFFFFFFF">
                    <UIControl Name="get" ClassName="CGUIStatic" Invisible="yes" Size_x="17" Size_y="15" Font="龙字体" TextRect_right="17" TextRect_bottom="15" TextColor="0xFFFFFFFF" ShadeColor="0xFF000000" PicFileName="data\ui\main\l_sz_02.bmp" PicRect_left="218" PicRect_top="196" PicRect_right="235" PicRect_bottom="211" PicColor="0xFFFFFFFF" />
                </UIControl>
                <UIControl Name="14" ClassName="CGUIStatic" LogicPos_x="81" LogicPos_y="17" Size_x="17" Size_y="15" Font="龙字体" TextRect_right="17" TextRect_bottom="15" TextColor="0xFFFFFFFF" ShadeColor="0xFF000000" TextAlign="Center" PicFileName="data\ui\main\l_sz_02.bmp" PicRect_left="237" PicRect_top="196" PicRect_right="254" PicRect_bottom="211" PicColor="0xFFFFFFFF">
                    <UIControl Name="get" ClassName="CGUIStatic" Invisible="yes" Size_x="17" Size_y="15" Font="龙字体" TextRect_right="17" TextRect_bottom="15" TextColor="0xFFFFFFFF" ShadeColor="0xFF000000" PicFileName="data\ui\main\l_sz_02.bmp" PicRect_left="218" PicRect_top="196" PicRect_right="235" PicRect_bottom="211" PicColor="0xFFFFFFFF" />
                </UIControl>
                <UIControl Name="15" ClassName="CGUIStatic" LogicPos_x="100" LogicPos_y="17" Size_x="17" Size_y="15" Font="龙字体" TextRect_right="17" TextRect_bottom="15" TextColor="0xFFFFFFFF" ShadeColor="0xFF000000" TextAlign="Center" PicFileName="data\ui\main\l_sz_02.bmp" PicRect_left="237" PicRect_top="196" PicRect_right="254" PicRect_bottom="211" PicColor="0xFFFFFFFF">
                    <UIControl Name="get" ClassName="CGUIStatic" Invisible="yes" Size_x="17" Size_y="15" Font="龙字体" TextRect_right="17" TextRect_bottom="15" TextColor="0xFFFFFFFF" ShadeColor="0xFF000000" PicFileName="data\ui\main\l_sz_02.bmp" PicRect_left="218" PicRect_top="196" PicRect_right="235" PicRect_bottom="211" PicColor="0xFFFFFFFF" />
                </UIControl>
                <UIControl Name="16" ClassName="CGUIStatic" LogicPos_x="119" LogicPos_y="17" Size_x="17" Size_y="15" Font="龙字体" TextRect_right="17" TextRect_bottom="15" TextColor="0xFFFFFFFF" ShadeColor="0xFF000000" TextAlign="Center" PicFileName="data\ui\main\l_sz_02.bmp" PicRect_left="237" PicRect_top="196" PicRect_right="254" PicRect_bottom="211" PicColor="0xFFFFFFFF">
                    <UIControl Name="get" ClassName="CGUIStatic" Invisible="yes" Size_x="17" Size_y="15" Font="龙字体" TextRect_right="17" TextRect_bottom="15" TextColor="0xFFFFFFFF" ShadeColor="0xFF000000" PicFileName="data\ui\main\l_sz_02.bmp" PicRect_left="218" PicRect_top="196" PicRect_right="235" PicRect_bottom="211" PicColor="0xFFFFFFFF" />
                </UIControl>
                <UIControl Name="17" ClassName="CGUIStatic" LogicPos_x="138" LogicPos_y="17" Size_x="17" Size_y="15" Font="龙字体" TextRect_right="17" TextRect_bottom="15" TextColor="0xFFFFFFFF" ShadeColor="0xFF000000" TextAlign="Center" PicFileName="data\ui\main\l_sz_02.bmp" PicRect_left="237" PicRect_top="196" PicRect_right="254" PicRect_bottom="211" PicColor="0xFFFFFFFF">
                    <UIControl Name="get" ClassName="CGUIStatic" Invisible="yes" Size_x="17" Size_y="15" Font="龙字体" TextRect_right="17" TextRect_bottom="15" TextColor="0xFFFFFFFF" ShadeColor="0xFF000000" PicFileName="data\ui\main\l_sz_02.bmp" PicRect_left="218" PicRect_top="196" PicRect_right="235" PicRect_bottom="211" PicColor="0xFFFFFFFF" />
                </UIControl>
                <UIControl Name="18" ClassName="CGUIStatic" LogicPos_x="157" LogicPos_y="17" Size_x="17" Size_y="15" Font="龙字体" TextRect_right="17" TextRect_bottom="15" TextColor="0xFFFFFFFF" ShadeColor="0xFF000000" TextAlign="Center" PicFileName="data\ui\main\l_sz_02.bmp" PicRect_left="237" PicRect_top="196" PicRect_right="254" PicRect_bottom="211" PicColor="0xFFFFFFFF">
                    <UIControl Name="get" ClassName="CGUIStatic" Invisible="yes" Size_x="17" Size_y="15" Font="龙字体" TextRect_right="17" TextRect_bottom="15" TextColor="0xFFFFFFFF" ShadeColor="0xFF000000" PicFileName="data\ui\main\l_sz_02.bmp" PicRect_left="218" PicRect_top="196" PicRect_right="235" PicRect_bottom="211" PicColor="0xFFFFFFFF" />
                </UIControl>
                <UIControl Name="19" ClassName="CGUIStatic" LogicPos_x="176" LogicPos_y="17" Size_x="17" Size_y="15" Font="龙字体" TextRect_right="17" TextRect_bottom="15" TextColor="0xFFFFFFFF" ShadeColor="0xFF000000" TextAlign="Center" PicFileName="data\ui\main\l_sz_02.bmp" PicRect_left="237" PicRect_top="196" PicRect_right="254" PicRect_bottom="211" PicColor="0xFFFFFFFF">
                    <UIControl Name="get" ClassName="CGUIStatic" Invisible="yes" Size_x="17" Size_y="15" Font="龙字体" TextRect_right="17" TextRect_bottom="15" TextColor="0xFFFFFFFF" ShadeColor="0xFF000000" PicFileName="data\ui\main\l_sz_02.bmp" PicRect_left="218" PicRect_top="196" PicRect_right="235" PicRect_bottom="211" PicColor="0xFFFFFFFF" />
                </UIControl>
            </UIControl>
            <UIControl Name="level" ClassName="CGUIStaticEx" LogicPos_x="70" LogicPos_y="253" Size_x="40" Size_y="16" Font="龙字体" FontHeight="14" TextRect_right="40" TextRect_bottom="16" TextColor="0xFFFCF157" ShadeColor="0xFF000000" TextAlign="Center" PicColor="0xFFFFFF" RowHeight="2" />
            <UIControl Name="word1" ClassName="CGUIStatic" LogicPos_x="70" LogicPos_y="270" Size_x="40" Size_y="16" Text="凝聚度" Font="龙字体" FontHeight="14" TextRect_right="40" TextRect_bottom="16" TextColor="0xFFFFFFFF" ShadeColor="0xFF000000" TextAlign="Center" PicColor="0xFFFFFF" />
            <UIControl Name="canclebutt" ClassName="CGUIButton" LogicPos_x="286" LogicPos_y="295" Size_x="74" Size_y="22" Text="关闭" Font="龙字体" FontHeight="16" TextRect_right="74" TextRect_bottom="22" TextColor="0xFFFFFFFF" ShadeColor="0xFF290404" TextAlign="Center" PicFileName="data\ui\common\l-common.bmp" PicRect_left="258" PicRect_right="332" PicRect_bottom="22" PicColor="0xFFFFFFFF" PushPicFileName="data\ui\common\l-common.bmp" PushPicRect_left="258" PushPicRect_top="44" PushPicRect_right="332" PushPicRect_bottom="66" PushPicColor="0xFFFFFFFF" PushTextColor="0xFFFFFFFF" PushShadeColor="0xFF290404" MovePicFileName="data\ui\common\l-common.bmp" MovePicRect_left="258" MovePicRect_top="22" MovePicRect_right="332" MovePicRect_bottom="44" MovePicColor="0xFFFFFFFF" MoveTextColor="0xFFFFFFFF" MoveShadeColor="0xFF290404" DisablePicFileName="data\ui\common\l-common.bmp" DisablePicRect_left="258" DisablePicRect_top="66" DisablePicRect_right="332" DisablePicRect_bottom="88" DisablePicColor="0xFFFFFFFF" DisableTextColor="0xFFFFFFFF" DisableShadeColor="0xFF290404" TopColor="0xFF000000" BottomColor="0xFFAFAFAF" />
            <UIControl Name="startbutt" ClassName="CGUIButton" LogicPos_x="196" LogicPos_y="295" Size_x="74" Size_y="22" Text="开始凝聚" Font="龙字体" FontHeight="16" TextRect_right="74" TextRect_bottom="22" TextColor="0xFFFFFFFF" ShadeColor="0xFF290404" TextAlign="Center" PicFileName="data\ui\common\l-common.bmp" PicRect_left="258" PicRect_right="332" PicRect_bottom="22" PicColor="0xFFFFFFFF" PushPicFileName="data\ui\common\l-common.bmp" PushPicRect_left="258" PushPicRect_top="44" PushPicRect_right="332" PushPicRect_bottom="66" PushPicColor="0xFFFFFFFF" PushTextColor="0xFFFFFFFF" PushShadeColor="0xFF290404" MovePicFileName="data\ui\common\l-common.bmp" MovePicRect_left="258" MovePicRect_top="22" MovePicRect_right="332" MovePicRect_bottom="44" MovePicColor="0xFFFFFFFF" MoveTextColor="0xFFFFFFFF" MoveShadeColor="0xFF290404" DisablePicFileName="data\ui\common\l-common.bmp" DisablePicRect_left="258" DisablePicRect_top="66" DisablePicRect_right="332" DisablePicRect_bottom="88" DisablePicColor="0xFFFFFFFF" DisableTextColor="0xFFFFFFFF" DisableShadeColor="0xFF290404" TopColor="0xFF000000" BottomColor="0xFFAFAFAF" />
            <UIControl Name="img0" ClassName="CGUIStatic" LogicPos_x="193" LogicPos_y="150" Size_x="15" Size_y="9" Font="龙字体" TextRect_right="15" TextRect_bottom="9" TextColor="0xFFFFF2A4" ShadeColor="0xFF290404" PicFileName="data\ui\main\l_sz_01.bmp" PicRect_left="544" PicRect_top="197" PicRect_right="559" PicRect_bottom="206" PicColor="0xFFFFFFFF" />
            <UIControl Name="img1" ClassName="CGUIStatic" LogicPos_x="193" LogicPos_y="185" Size_x="15" Size_y="9" Font="龙字体" TextRect_right="15" TextRect_bottom="9" TextColor="0xFFFFF2A4" ShadeColor="0xFF290404" PicFileName="data\ui\main\l_sz_01.bmp" PicRect_left="544" PicRect_top="197" PicRect_right="559" PicRect_bottom="206" PicColor="0xFFFFFFFF" />
            <UIControl Name="pic" ClassName="CGUIStatic" LogicPos_x="168" LogicPos_y="50" Size_x="64" Size_y="64" Font="龙字体" TextRect_right="128" TextRect_bottom="128" TextColor="0xFFFFF2A4" ShadeColor="0xFF290404" PicFileName="data\ui\main\l_sz_01.bmp" PicRect_left="807" PicRect_right="871" PicRect_bottom="64" PicColor="0xFFFFFFFF" />
            <UIControl Name="exp" ClassName="CGUIStatic" LogicPos_x="145" LogicPos_y="125" Size_x="110" Size_y="20" Text="信仰" Font="龙字体" FontHeight="15" TextRect_right="110" TextRect_bottom="20" TextColor="0xFFFFFFFF" ShadeColor="0xFF000000" TextAlign="LeftCenter" PicColor="0xFFFFFF">
                <UIControl Name="num" ClassName="CGUIStatic" LogicPos_x="45" Size_x="65" Size_y="20" Font="龙字体" FontHeight="16" TextRect_right="65" TextRect_bottom="20" TextColor="0xFFFCF157" ShadeColor="0xFF000000" TextAlign="Center" PicColor="0xFFFFFF" />
            </UIControl>
            <UIControl Name="progpic1" ClassName="CGUIStatic" LogicPos_x="120" LogicPos_y="210" Size_x="160" Size_y="12" Font="龙字体" TextRect_right="190" TextRect_bottom="12" TextColor="0xFFFFF2A4" ShadeColor="0xFF290404" TextAlign="Center" PicFileName="data\ui\main\l-main02.bmp" PicRect_left="128" PicRect_top="7" PicRect_right="327" PicRect_bottom="18" PicColor="0xFFFFFFFF" AlphaWrite="Write">
                <UIControl Name="proqress" ClassName="CGUIProgress" MoveFather="yes" LogicPos_x="3" LogicPos_y="2" Size_x="154" Size_y="8" Font="龙字体" TextRect_right="189" TextRect_bottom="5" TextColor="0xFFFFF2A4" ShadeColor="0xFF290404" PicFileName="data\ui\common\l-common.bmp" PicRect_top="316" PicRect_right="142" PicRect_bottom="323" PicColor="0xFF7B714A" AlphaWrite="Write" Horizon="yes" ForePicFileName="data\ui\common\l_jindu-glass-b.bmp" ForePicColor="0xFFFFFFFF" />
            </UIControl>
            <UIControl Name="progpic0" ClassName="CGUIStatic" LogicPos_x="137" LogicPos_y="272" Size_x="190" Size_y="12" Font="龙字体" TextRect_right="190" TextRect_bottom="12" TextColor="0xFFFFF2A4" ShadeColor="0xFF290404" TextAlign="Center" PicFileName="data\ui\main\l-main02.bmp" PicRect_left="128" PicRect_top="7" PicRect_right="327" PicRect_bottom="18" PicColor="0xFFFFFFFF" AlphaWrite="Write">
                <UIControl Name="num" ClassName="CGUIStatic" TopMost="yes" LogicPos_x="45" Size_x="100" Size_y="12" Font="龙字体" FontHeight="16" TextRect_right="100" TextRect_bottom="12" TextColor="0xFFFFFFFF" ShadeColor="0xFF290404" TextAlign="Center" PicColor="0xFFFFFF" />
                <UIControl Name="proqress" ClassName="CGUIProgress" MoveFather="yes" LogicPos_x="3" LogicPos_y="2" Size_x="184" Size_y="8" Font="龙字体" TextRect_right="189" TextRect_bottom="5" TextColor="0xFFFFF2A4" ShadeColor="0xFF290404" PicFileName="data\ui\common\l-common.bmp" PicRect_top="316" PicRect_right="142" PicRect_bottom="323" PicColor="0xFF7B714A" AlphaWrite="Write" Horizon="yes" ForePicFileName="data\ui\common\l-common.bmp" ForePicRect_top="293" ForePicRect_right="188" ForePicRect_bottom="297" ForePicColor="0xFFFFFFFF" />
            </UIControl>
        </UIControl>
    </UIControl>
</desktop>
